{"is_source_file": true, "format": "JavaScript (React JSX)", "description": "This file defines a React functional component 'Settings' that implements the user settings page, including profile info, notification preferences, alert configurations, security (password change), and appearance (theme toggle). It manages state with React hooks, interacts with backend APIs via axios, and uses custom context hooks for auth, theme, and notifications.", "external_files": ["../context/AuthContext", "../context/ThemeContext", "../context/NotificationContext", "./Settings.css"], "external_methods": ["useAuth", "useTheme", "useNotifications", "axios.get", "axios.put", "updateUser", "requestNotificationPermission", "toggleTheme"], "published": ["Settings"], "classes": [], "methods": [{"name": "fetchSettings", "description": "Fetches user settings from the API and updates state for notifications and alerts."}, {"name": "handleProfileUpdate", "description": "Submits updated profile data to the API and updates user context."}, {"name": "handleNotificationUpdate", "description": "Saves notification preferences and requests notification permissions if push notifications are enabled."}, {"name": "handleAlertUpdate", "description": "Saves alert preferences to the backend."}, {"name": "handlePasswordChange", "description": "Handles password change request, validating confirmation and sending update to API."}], "calls": ["axios.get('/api/user/settings')", "axios.put('/api/user/profile', profileData)", "axios.put('/api/user/notifications', notificationSettings)", "axios.put('/api/user/alert-settings', alertSettings)", "axios.put('/api/user/password', {...})", "updateUser(response.data)", "requestNotificationPermission()", "toggleTheme()"], "search-terms": ["Settings React component", "user profile form", "notification preferences toggle", "alert configuration", "security/password change", "appearance theme toggle", "axios API calls"], "state": 2, "file_id": 29, "knowledge_revision": 80, "git_revision": "068251a05407f5b9be91b15c6659d6d76d371387", "revision_history": [{"64": ""}, {"80": "068251a05407f5b9be91b15c6659d6d76d371387"}], "ctags": [{"_type": "tag", "name": "Settings", "path": "/home/kavia/workspace/code-generation/ticket-alert-pro-121529-121538/tickethawk_frontend/src/pages/Settings.js", "pattern": "/^const Settings = () => {$/", "language": "JavaScript", "kind": "constant"}, {"_type": "tag", "name": "fetchSettings", "path": "/home/kavia/workspace/code-generation/ticket-alert-pro-121529-121538/tickethawk_frontend/src/pages/Settings.js", "pattern": "/^  const fetchSettings = async () => {$/", "language": "JavaScript", "kind": "constant"}, {"_type": "tag", "name": "handleAlertUpdate", "path": "/home/kavia/workspace/code-generation/ticket-alert-pro-121529-121538/tickethawk_frontend/src/pages/Settings.js", "pattern": "/^  const handleAlertUpdate = async () => {$/", "language": "JavaScript", "kind": "constant"}, {"_type": "tag", "name": "handleNotificationUpdate", "path": "/home/kavia/workspace/code-generation/ticket-alert-pro-121529-121538/tickethawk_frontend/src/pages/Settings.js", "pattern": "/^  const handleNotificationUpdate = async () => {$/", "language": "JavaScript", "kind": "constant"}, {"_type": "tag", "name": "handlePasswordChange", "path": "/home/kavia/workspace/code-generation/ticket-alert-pro-121529-121538/tickethawk_frontend/src/pages/Settings.js", "pattern": "/^  const handlePasswordChange = async (e) => {$/", "language": "JavaScript", "kind": "constant"}, {"_type": "tag", "name": "handleProfileUpdate", "path": "/home/kavia/workspace/code-generation/ticket-alert-pro-121529-121538/tickethawk_frontend/src/pages/Settings.js", "pattern": "/^  const handleProfileUpdate = async (e) => {$/", "language": "JavaScript", "kind": "constant"}, {"_type": "tag", "name": "response", "path": "/home/kavia/workspace/code-generation/ticket-alert-pro-121529-121538/tickethawk_frontend/src/pages/Settings.js", "pattern": "/^      const response = await axios.get('\\/api\\/user\\/settings');$/", "language": "JavaScript", "kind": "constant"}, {"_type": "tag", "name": "response", "path": "/home/kavia/workspace/code-generation/ticket-alert-pro-121529-121538/tickethawk_frontend/src/pages/Settings.js", "pattern": "/^      const response = await axios.put('\\/api\\/user\\/profile', profileData);$/", "language": "JavaScript", "kind": "constant"}, {"_type": "tag", "name": "setActiveTab", "path": "/home/kavia/workspace/code-generation/ticket-alert-pro-121529-121538/tickethawk_frontend/src/pages/Settings.js", "pattern": "/^  const [activeTab, setActiveTab] = useState('profile');$/", "language": "JavaScript", "kind": "constant"}, {"_type": "tag", "name": "setAlertSettings", "path": "/home/kavia/workspace/code-generation/ticket-alert-pro-121529-121538/tickethawk_frontend/src/pages/Settings.js", "pattern": "/^  const [alertSettings, setAlertSettings] = useState({$/", "language": "JavaScript", "kind": "constant"}, {"_type": "tag", "name": "setLoading", "path": "/home/kavia/workspace/code-generation/ticket-alert-pro-121529-121538/tickethawk_frontend/src/pages/Settings.js", "pattern": "/^  const [loading, setLoading] = useState(false);$/", "language": "JavaScript", "kind": "constant"}, {"_type": "tag", "name": "setMessage", "path": "/home/kavia/workspace/code-generation/ticket-alert-pro-121529-121538/tickethawk_frontend/src/pages/Settings.js", "pattern": "/^  const [message, setMessage] = useState({ type: '', text: '' });$/", "language": "JavaScript", "kind": "constant"}, {"_type": "tag", "name": "setNotificationSettings", "path": "/home/kavia/workspace/code-generation/ticket-alert-pro-121529-121538/tickethawk_frontend/src/pages/Settings.js", "pattern": "/^  const [notificationSettings, setNotificationSettings] = useState({$/", "language": "JavaScript", "kind": "constant"}, {"_type": "tag", "name": "setPasswordData", "path": "/home/kavia/workspace/code-generation/ticket-alert-pro-121529-121538/tickethawk_frontend/src/pages/Settings.js", "pattern": "/^  const [passwordData, setPasswordData] = useState({$/", "language": "JavaScript", "kind": "constant"}, {"_type": "tag", "name": "setProfileData", "path": "/home/kavia/workspace/code-generation/ticket-alert-pro-121529-121538/tickethawk_frontend/src/pages/Settings.js", "pattern": "/^  const [profileData, setProfileData] = useState({$/", "language": "JavaScript", "kind": "constant"}, {"_type": "tag", "name": "tabs", "path": "/home/kavia/workspace/code-generation/ticket-alert-pro-121529-121538/tickethawk_frontend/src/pages/Settings.js", "pattern": "/^  const tabs = [$/", "language": "JavaScript", "kind": "constant"}], "hash": "e37c01bde90559d884250e6230d44e38", "format-version": 4, "code-base-name": "tickethawk_frontend", "filename": "tickethawk_frontend/src/pages/Settings.js"}